{
	"variants": {
	"lycanitesmobs:textures/entity/vapula.png": "outlined_sprite:vapula_icon.png" ,
	"lycanitesmobs:textures/entity/vapula_golden.png": "outlined_sprite:vapula_golden_icon.png" ,
	"lycanitesmobs:textures/entity/vapula_verdant.png": "outlined_sprite:vapula_verdant_icon.png"
	},
	
	 "modelConfigs": [
		{
		  "baseScale": 1.0,
		  "rotationY": 0,
		  "rotationX": 0,
		  "rotationZ": 0,
		  "offsetX": 0,
		  "offsetY": 0,
		  "modelPartsFields": [],
		  "modelMainPartFieldAliases": [],
		  "modelRootPath": [[]],
		  "renderingFullModel": false,
		  "modelPartsRotationReset": true,
		  "layersAllowed": true
		}
	]
}